scale/__init__.py
scale/data.py
scale/function.py
scale/logger.py
scale/metrics.py
scale/plot.py
scale/net/__init__.py
scale/net/layer.py
scale/net/loss.py
scale/net/utils.py
scale/net/vae.py
scale_v2-2.0.3.dev0.data/scripts/SCALE.py
scale_v2-2.0.3.dev0.dist-info/LICENSE.txt
scale_v2-2.0.3.dev0.dist-info/METADATA
scale_v2-2.0.3.dev0.dist-info/WHEEL
scale_v2-2.0.3.dev0.dist-info/top_level.txt
scale_v2-2.0.3.dev0.dist-info/RECORD
