Metadata-Version: 2.1
Name: scale-v2
Version: 2.0.3.dev0
Summary: Single-cell integrative Analysis via Latent feature Extraction
Home-page: https://github.com/jsxlei/scale_v2
Author: Lei Xiong
Author-email: jsxlei@gmail.com
License: MIT
Platform: UNKNOWN
Classifier: Development Status :: 4 - Beta
Classifier: Intended Audience :: Science/Research
Classifier: License :: OSI Approved :: MIT License
Classifier: Programming Language :: Python :: 3.7
Classifier: Operating System :: MacOS :: MacOS X
Classifier: Operating System :: Microsoft :: Windows
Classifier: Operating System :: POSIX :: Linux
Classifier: Topic :: Scientific/Engineering :: Bio-Informatics
Requires-Python: >3.6.0
Requires-Dist: numpy (>=1.17.2)
Requires-Dist: pandas (>=0.25.1)
Requires-Dist: scipy (>=1.3.1)
Requires-Dist: scikit-learn (>=0.22.1)
Requires-Dist: torch (>=1.0.0)
Requires-Dist: scanpy (>=1.4.5)
Requires-Dist: tqdm (>=4.28.1)
Requires-Dist: matplotlib (>=3.0.3)
Requires-Dist: seaborn (>=0.9.0)
Requires-Dist: leidenalg (>=0.8.3)
Requires-Dist: episcanpy (>=0.3.0)
